file_routes/__init__.py
file_routes/directoryvisitor.py
file_routes/filerouteinfo.py
file_routes/inspection.py
file_routes/py.typed
file_routes/route.py
file_routes/utils.py
file_routes/frameworks/__init__.py
file_routes/frameworks/django.py
file_routes/frameworks/flask.py
file_routes/tests/django_settings.py
file_routes/tests/test_routes.py
file_routes-0.1.6.dist-info/METADATA
file_routes-0.1.6.dist-info/WHEEL
file_routes-0.1.6.dist-info/licenses/LICENSE
file_routes-0.1.6.dist-info/RECORD
