Metadata-Version: 2.1
Name: file_routes
Version: 0.1.6
Summary: File system based routing for Django & Flask
Project-URL: repository, https://github.com/jdahlin/file-routes
Author-email: Johan Dahlin <jdahlin@gmail.com>
License-Expression: MIT
License-File: LICENSE
Classifier: Development Status :: 2 - Pre-Alpha
Classifier: Environment :: Web Environment
Classifier: Framework :: Django
Classifier: Framework :: Flask
Classifier: Intended Audience :: Developers
Classifier: License :: OSI Approved :: BSD License
Classifier: Operating System :: OS Independent
Classifier: Programming Language :: Python
Classifier: Programming Language :: Python :: 3 :: Only
Classifier: Programming Language :: Python :: 3.10
Classifier: Programming Language :: Python :: 3.11
Classifier: Topic :: Internet :: WWW/HTTP
Classifier: Topic :: Software Development
Classifier: Topic :: Software Development :: Libraries
Classifier: Topic :: Software Development :: Libraries :: Application Frameworks
Classifier: Topic :: Software Development :: Libraries :: Python Modules
Classifier: Typing :: Typed
Requires-Python: >=3.8
Provides-Extra: dev
Requires-Dist: black==22.12.0; extra == 'dev'
Requires-Dist: coverage[toml]<8.0,>=6.5.0; extra == 'dev'
Requires-Dist: django-stubs>=1.13.1; extra == 'dev'
Requires-Dist: isort<6.0.0,>=5.0.6; extra == 'dev'
Requires-Dist: mypy==0.991; extra == 'dev'
Requires-Dist: pytest-django==4.5.2; extra == 'dev'
Requires-Dist: pytest<8.0.0,>=7.1.3; extra == 'dev'
Requires-Dist: ruff==0.0.219; extra == 'dev'
Provides-Extra: django
Requires-Dist: django>=4.0; extra == 'django'
Provides-Extra: flask
Requires-Dist: flask>=2.2; extra == 'flask'
